MANIFEST.in
setup.py
docs/HISTORY.txt
src/dolmen/__init__.py
src/dolmen.security.policies.egg-info/PKG-INFO
src/dolmen.security.policies.egg-info/SOURCES.txt
src/dolmen.security.policies.egg-info/dependency_links.txt
src/dolmen.security.policies.egg-info/entry_points.txt
src/dolmen.security.policies.egg-info/namespace_packages.txt
src/dolmen.security.policies.egg-info/not-zip-safe
src/dolmen.security.policies.egg-info/requires.txt
src/dolmen.security.policies.egg-info/top_level.txt
src/dolmen/security/__init__.py
src/dolmen/security/policies/README.txt
src/dolmen/security/policies/__init__.py
src/dolmen/security/policies/ftesting.zcml
src/dolmen/security/policies/interfaces.py
src/dolmen/security/policies/principalrole.py
src/dolmen/security/policies/rolepermission.py
src/dolmen/security/policies/tests.py