Metadata-Version: 1.0
Name: dolmen.security.policies
Version: 0.3
Summary: A collection of security maps baseclasses
Home-page: http://www.dolmen-project.org
Author: Souheil Chelfouh
Author-email: trollfot@gmail.com
License: GPL
Keywords: Grok security
Platform: Any
Classifier: Programming Language :: Python
